package_a/__init__.py
package_a/age_calculator.py
package_a/greet_function.py
package_a/tax_calculator.py
package_a/test_functions.py
learn_python_package_bhupesh-0.5.dist-info/METADATA
learn_python_package_bhupesh-0.5.dist-info/WHEEL
learn_python_package_bhupesh-0.5.dist-info/top_level.txt
learn_python_package_bhupesh-0.5.dist-info/RECORD
