Metadata-Version: 2.1
Name: learn_python_package_bhupesh
Version: 0.5
Summary: package created for learning purposes
Home-page: https://github.com/BhupeshTongaria/Learn_python_package/
Author: Bhupesh Tongaria
